ergoflo/__init__.py
ergoflo/flow.py
ergoflo/option.py
ergoflo/result.py
ergoflo/tests/test_flow.py
ergoflo/tests/test_option.py
ergoflo/tests/test_result.py
ergoflo-0.1.0.dist-info/METADATA
ergoflo-0.1.0.dist-info/WHEEL
ergoflo-0.1.0.dist-info/RECORD
